tc_transform/__init__.py
tc_transform-0.2.0.dist-info/METADATA
tc_transform-0.2.0.dist-info/WHEEL
tc_transform-0.2.0.dist-info/RECORD
